chafon_rfid/__init__.py
chafon_rfid/base.py
chafon_rfid/checksum.py
chafon_rfid/command.py
chafon_rfid/response.py
chafon_rfid/transport.py
chafon_rfid/transport_microbit.py
chafon_rfid/transport_serial.py
chafon_rfid/uhfreader18.py
chafon_rfid/uhfreader288m.py
tests/__init__.py
tests/test_base.py
tests/test_uhfreader18.py
tests/test_uhfreader288.py
wabson.chafon_rfid-0.1.0.dist-info/LICENSE
wabson.chafon_rfid-0.1.0.dist-info/METADATA
wabson.chafon_rfid-0.1.0.dist-info/WHEEL
wabson.chafon_rfid-0.1.0.dist-info/top_level.txt
wabson.chafon_rfid-0.1.0.dist-info/RECORD
