Metadata-Version: 2.1
Name: wabson.chafon-rfid
Version: 0.1.0
Summary: Read RFID data from Chafon UHF readers
Home-page: https://github.com/wabson/chafon-rfid
Author: Will Abson
Author-email: will@wabson.org
License: UNKNOWN
Platform: UNKNOWN
Classifier: Development Status :: 3 - Alpha
Classifier: Programming Language :: Python :: 3
Classifier: Programming Language :: Python :: 3.4
Classifier: Programming Language :: Python :: 3.5
Classifier: Programming Language :: Python :: 3.6
Classifier: License :: OSI Approved :: MIT License
Classifier: Operating System :: OS Independent
Requires-Python: >=3.4
Provides-Extra: test
